dataprocessingml/__init__.py
dataprocessingml-0.1.dist-info/LICENCE.txt
dataprocessingml-0.1.dist-info/METADATA
dataprocessingml-0.1.dist-info/WHEEL
dataprocessingml-0.1.dist-info/top_level.txt
dataprocessingml-0.1.dist-info/RECORD
