Metadata-Version: 2.1
Name: dataprocessingml
Version: 0.1
Summary: Basic Machine Learing data processing
Home-page: UNKNOWN
Author: Sumit Kumar sahoo
Author-email: sumitlala99@gmail.com
License: UNKNOWN
Platform: UNKNOWN
Classifier: Programming Language :: Python :: 3
Classifier: License :: OSI Approved :: MIT License
Classifier: Operating System :: OS Independent
